{
    "Surprise Trip to Fort Lauderdale, FL": 
        {
            "name": "Surprise Trip to Fort Lauderdale, FL",
            "description": "Xue surprised me with this trip! We visited Fort Lauderdale as a way of rewarding ourselves for our hard work so far as professionals in the labor force. This trip was our first official trip together as a couple, alone, where we flew somewhere together just us!",
            "locations": [
                {
                    "country": "United States of America",
                    "state": "Florida",
                    "city": "Fort Lauderdale"
                }
            ],
            "start_date": {
                "month": 12,
                "day": 2,
                "year": 2022
            },
            "end_date": {
                "month": 12,
                "day": 6,
                "year": 2022
            },
            "added_by": "Mandy",
            "primary_photo": "",
            "photos": [
                "IMG_5145.HEIC",
                "IMG_5154.HEIC",
                "IMG_5184.HEIC",
                "IMG_5185.HEIC",
                "IMG_5221.HEIC",
                "IMG_5223.HEIC",
                "IMG_5225.HEIC",
                "IMG_5227.HEIC",
                "IMG_5231.JPG",
                "IMG_5236.HEIC",
                "IMG_5237.HEIC",
                "IMG_5248.HEIC",
                "IMG_5251.HEIC",
                "IMG_5252.HEIC",
                "IMG_5253.HEIC",
                "IMG_5254.HEIC",
                "IMG_5255.HEIC",
                "IMG_5256.HEIC",
                "IMG_5257.HEIC",
                "IMG_5258.HEIC"
            ]
        },
    "Providence, RI to Minnapolis, MN Road Trip":
        {
            "name": "Providence, RI to Minnapolis, MN Road Trip",
            "description": "After my graduation from Brown in Providence, Rhode Island, Xue drove with me (and all my stuff!) all the way back to Minneapolis. It was our first real trip together as a couple and our first road trip together too, just us. It was so much fun and we got to know each other a lot better, just driving and talking together.",
            "locations": [
                {
                    "country": "United States of America",
                    "state": "Rhode Island",
                    "city": "Providence"
                },
                {
                    "country": "United States of America",
                    "state": "Ohio",
                    "city": "Cleveland"
                },
                {
                    "country": "United States of America",
                    "state": "Illinois",
                    "city": "Chicago"
                },
                {
                    "country": "United States of America",
                    "state": "Minnesota",
                    "city": "Minneapolis"
                }
            ],
            "start_date": {
                "month": 5,
                "day": 31,
                "year": 2022
            },
            "end_date": {
                "month": 6,
                "day": 5,
                "year": 2022
            },
            "added_by": "Mandy",
            "primary_photo": "",
            "photos": [
                "IMG_3157.HEIC",
                "IMG_3176.HEIC",
                "IMG_3181.JPG",
                "IMG_3182.JPG",
                "IMG_3188.HEIC",
                "IMG_3196.JPG",
                "IMG_3208.HEIC",
                "IMG_3216.HEIC",
                "IMG_3230.HEIC",
                "IMG_3234.JPG"
            ]
        },
    "Mandy's Graduation": 
        {
            "name": "Mandy's Graduation",
            "description": "My family and Xue came all the way from Minnesota to Providence, RI to celebrate my graduation from Brown University!",
            "locations": [
                {
                    "country": "United States of America",
                    "state": "Rhode Island",
                    "city": "Providence"
                }
            ],
            "start_date": {
                "month": 5,
                "day": 28,
                "year": 2022
            },
            "end_date": {
                "month": 6,
                "day": 1,
                "year": 2022
            },
            "added_by": "Mandy",
            "primary_photo": "",
            "photos": [
                "CVTU8714.JPG",
                "IMG_2593.HEIC",
                "IMG_2594.HEIC",
                "IMG_3060.HEIC",
                "IMG_3097.JPG",
                "IMG_3099.JPG",
                "IMG_3139.JPG"
            ]
        },
    "Hike at Taylors Falls with Mandy's Family": 
        {
            "name": "Hike at Taylors Falls with Mandy's Family",
            "description": "Xue tagged along with Mandy's family to go on a hike at Taylors Falls state park. It was his first extended trip with her family and it meant a lot to her because he really got to know her family well and they got to know him better too!",
            "locations": [
                {
                    "country": "United States of America",
                    "state": "Minnesota",
                    "city": "Taylors Falls"
                }
            ],
            "start_date": {
                "month": 6,
                "day": 19,
                "year": 2020
            },
            "end_date": {
                "month": 6,
                "day": 19,
                "year": 2020
            },
            "added_by": "Mandy",
            "primary_photo": "DSC0086.JPG",
            "photos": [
                "DSC0080.JPG",
                "DSC0086.JPG",
                "DSC00109.JPG",
                "DSC00114.JPG",
                "DSC00141.JPG",
                "DSC00142.JPG",
                "DSC00150.JPG",
                "DSC00152.JPG",
                "DSC00154.JPG",
                "DSC00155.JPG",
                "DSC00159.JPG",
                "DSC00160.JPG",
                "DSC00162.JPG",
                "DSC00182.JPG",
                "DSC00184.JPG",
                "DSC00186.JPG",
                "DSC00198.JPG",
                "DSC00204.JPG",
                "DSC00205.JPG",
                "DSC00206.JPG",
                "DSC00207.JPG",
                "DSC00208.JPG",
                "DSC00209.JPG",
                "DSC00234.JPG",
                "DSC00236.JPG",
                "DSC00237.JPG",
                "DSC00238.JPG",
                "DSC00239.JPG",
                "DSC00240.JPG",
                "DSC00241.JPG",
                "DSC00242.JPG",
                "DSC00243.JPG",
                "DSC00245.JPG",
                "DSC00259.JPG",
                "DSC00261.JPG",
                "DSC00276.JPG",
                "DSC00277.JPG",
                "DSC00298.JPG",
                "DSC00299.JPG",
                "DSC00316.JPG",
                "DSC00317.JPG",
                "DSC00335.JPG",
                "DSC00337.JPG",
                "DSC00345.JPG",
                "DSC00347.JPG",
                "DSC00350.JPG",
                "DSC00351.JPG",
                "DSC00353.JPG",
                "DSC00366.JPG",
                "DSC00374.JPG",
                "DSC00397.JPG",
                "DSC00398.JPG",
                "DSC00399.JPG",
                "DSC00400.JPG",
                "DSC00413.JPG",
                "DSC00414.JPG",
                "DSC00415.JPG",
                "DSC00430.JPG",
                "DSC00434.JPG",
                "DSC00478.JPG",
                "DSC00487.JPG",
                "DSC00488.JPG",
                "DSC00490.JPG",
                "DSC00492.JPG",
                "DSC00493.JPG",
                "DSC00494.JPG",
                "DSC00516.JPG",
                "DSC00540.JPG",
                "DSC00646.JPG",
                "DSC00650.JPG",
                "DSC00652.JPG",
                "DSC00654.JPG",
                "DSC00655.JPG",
                "DSC00656.JPG",
                "DSC00657.JPG",
                "DSC00659.JPG"
            ]
        },
    "Xue Visits Mandy in Providence During Senior Year, Part 1":
        {
            "name": "Xue Visits Mandy in Providence During Senior Fall",
            "description": "Xue came to Providence to visit Mandy during their fall semester of their senior year!",
            "locations": [
                {
                    "country": "United States of America",
                    "state": "Rhode Island",
                    "city": "Providence"
                }
            ],
            "start_date": {
                "month": 10,
                "day": null,
                "year": 2021
            },
            "end_date": {
                "month": 10,
                "day": null,
                "year": 2021
            },
            "added_by": "Mandy",
            "primary_photo": "IMG_1418.HEIC",
            "photos": [
                "IMG_1418.HEIC",
                "IMG_1419.HEIC",
                "IMG_1421.HEIC",
                "IMG_1423.HEIC",
                "IMG_1424.HEIC",
                "IMG_1425.HEIC",
                "IMG_1433.JPG",
                "IMG_1434.JPG",
                "IMG_1457.HEIC"
            ]
        },
    "Xue Visits Mandy in Providence During Senior Year, Part 2":
        {
            "name": "Xue Visits Mandy in Providence During Senior Spring",
            "description": "Xue came to Providence to visit Mandy during their senior year, but this time, it was in the spring semester! This visit was basically two years after he had visited her at Brown for the first time.",
            "locations": [
                {
                    "country": "United States of America",
                    "state": "Rhode Island",
                    "city": "Providence"
                }
            ],
            "start_date": {
                "month": 3,
                "day": null,
                "year": 2022
            },
            "end_date": {
                "month": 3,
                "day": null,
                "year": 2022
            },
            "added_by": "Mandy",
            "primary_photo": "",
            "photos": [
                "IMG_2407.HEIC",
                "IMG_2409.HEIC",
                "IMG_2431.HEIC",
                "IMG_2434.HEIC",
                "IMG_2437.JPG",
                "IMG_2445.HEIC",
                "IMG_2446.HEIC",
                "IMG_2446.HEIC",
                "IMG_2449.HEIC",
                "IMG_2451.JPG",
                "IMG_2453.JPG",
                "IMG_2458.JPG",
                "IMG_2463.JPG",
                "IMG_2470.JPG",
                "IMG_2471.HEIC",
                "IMG_2472.HEIC"
            ]
        },
    "Dang Thao Tour: Final Two Shows":
        {
            "name": "Dang Thao Tour: Final Two Shows",
            "description": "Mandy tagged along with Xue to Sacramento, CA and Fresno, CA to watch him and his brothers play for Dang Thao.",
            "locations": [
                {
                    "country": "United States of America",
                    "state": "California",
                    "city": "Sacramento"
                },
                {
                    "country": "United States of America",
                    "state": "California",
                    "city": "Fresno"
                }
            ],
            "start_date": {
                "month": 11,
                "day": null,
                "year": 2022
            },
            "end_date": {
                "month": 1,
                "day": null,
                "year": 2023
            },
            "added_by": "Mandy",
            "primary_photo": "placeholder.png",
            "photos": [
                "IMG_5042.HEIC",
                "IMG_5046.HEIC",
                "IMG_5049.HEIC",
                "IMG_5073.HEIC",
                "IMG_5080.HEIC",
                "IMG_5086.JPG",
                "IMG_5087.HEIC",
                "IMG_5096.HEIC",
                "IMG_5097.HEIC",
                "IMG_5101.HEIC"
            ]
        }  
}